{
  "type": "minecraft:entity",
  "pools": [
    {
      "rolls": 1,
      "entries": [
        {
          "type": "minecraft:item",
          "functions": [
            {
              "function": "minecraft:set_count",
              "count": {
                "min": 0.0,
                "max": 5.0,
                "type": "minecraft:uniform"
              }
            },
            {
              "function": "minecraft:looting_enchant",
              "count": {
                "min": 0.0,
                "max": 3.0
              }
            }
          ],
          "name": "minecraft:leather"
        }
      ]
    },
    {
      "rolls": 1,
      "entries": [
        {
          "type": "minecraft:item",
          "name": "minecraft:clock"
        },
        {
          "type": "minecraft:item",
          "name": "minecraft:carrot"
        },
        {
          "type": "minecraft:item",
          "name": "minecraft:potato"
        },
        {
          "type": "minecraft:item",
          "name": "minecraft:wheat"
        },
        {
          "type": "minecraft:item",
          "name": "ervin_mod_1:targ"
        },
        {
          "type": "minecraft:item",
          "name": "ervin_mod_1:volmint"
        }
      ],
      "conditions": [
        {
          "condition": "minecraft:killed_by_player"
        },
        {
          "condition": "minecraft:random_chance_with_looting",
          "chance": 0.025,
          "looting_multiplier": 0.01
        }
      ]
    },
    {
      "rolls": 1,
      "entries": [
        {
          "type": "minecraft:item",
          "name": "minecraft:bat_spawn_egg"
        }
      ],
      "conditions": [
        {
          "condition": "minecraft:killed_by_player"
        },
        {
          "condition": "minecraft:random_chance_with_looting",
          "chance": 0.0025,
          "looting_multiplier": 0.001
        }
      ]
    }
  ]
}
